requirements/base.txt
requirements/super_resolution.txt
solafune_tools/__init__.py
solafune_tools/image_fetcher.py
solafune_tools/junk.py
solafune_tools/make_catalog.py
solafune_tools/make_mosaic.py
solafune_tools/metrics.py
solafune_tools/pipeline.py
solafune_tools/settings.py
solafune_tools/community_tools/__init__.py
solafune_tools/competition_tools/__init__.py
solafune_tools/competition_tools/quality_checker.py
solafune_tools/competition_tools/solafune_dataset.py
solafune_tools/osm/__init__.py
solafune_tools/osm/super_resolution/__init__.py
solafune_tools/osm/super_resolution/common_utils.py
solafune_tools/osm/super_resolution/config.py
solafune_tools/osm/super_resolution/create_dataset.py
solafune_tools/osm/super_resolution/inference.py
solafune_tools/osm/super_resolution/model.py
solafune_tools/osm/super_resolution/preprocess.py
solafune_tools/osm/super_resolution/train.py
solafune_tools/osm/super_resolution/train_src/train_continue.py
solafune_tools/osm/super_resolution/train_src/train_end.py
solafune_tools/osm/super_resolution/train_src/train_step1.py
solafune_tools/osm/super_resolution/train_src/train_step2.py
solafune_tools/osm/super_resolution/train_src/train_step3.py
solafune_tools/osm/super_resolution/train_src/train_step4.py
solafune_tools-0.9.2.dist-info/licenses/LICENSE
tests/__init__.py
tests/mock_get_catalog.py
tests/test_competition_tools.py
tests/test_make_mosaic.py
tests/test_metrics.py
tests/test_settings.py
tests/test_write_catalog.py
tests/test_osm/test_super_resolution.py
solafune_tools-0.9.2.dist-info/METADATA
solafune_tools-0.9.2.dist-info/WHEEL
solafune_tools-0.9.2.dist-info/top_level.txt
solafune_tools-0.9.2.dist-info/RECORD
