Metadata-Version: 2.4
Name: solafune-tools
Version: 0.9.2
Summary: Open tools for Solafune developers and Solafune hackers where can share developed tools in geospatial data
Author-email: Pushkar Kopparla <pushkar.kopparla@solafune.com>, Toru Mitsutake <toru.mitsutake@solafune.com>, Lanang Afkaar <afkaar.lanang@solafune.com>
Requires-Python: >=3.10
License-File: LICENSE
Requires-Dist: dask<2025.4.1,>=2024.9.0
Requires-Dist: geopandas<=1.0.1
Requires-Dist: pillow<11.2.0,>=10.0.0
Requires-Dist: planetary_computer<=1.0.0
Requires-Dist: pystac<=1.12.2
Requires-Dist: pystac_client<=0.8.6
Requires-Dist: requests<=2.32.3
Requires-Dist: rioxarray<=0.18.2
Requires-Dist: stac_geoparquet<=0.6.0
Requires-Dist: stackstac<=0.5.1
Requires-Dist: shapely<=2.0.7
Requires-Dist: numpy<=1.26.4
Requires-Dist: tqdm<=4.67.1
Requires-Dist: rasterio<=1.4.3
Provides-Extra: super-resolution
Requires-Dist: torch>=2.6.0; extra == "super-resolution"
Requires-Dist: torchvision>=0.22.1; extra == "super-resolution"
Requires-Dist: torchaudio>=2.6.0; extra == "super-resolution"
Requires-Dist: opencv-python>=4.11.0.86; extra == "super-resolution"
Requires-Dist: scikit-image>=0.22.0; extra == "super-resolution"
Requires-Dist: tqdm>=4.66.1; extra == "super-resolution"
Requires-Dist: madgrad==1.3; extra == "super-resolution"
Requires-Dist: matplotlib==3.8.1; extra == "super-resolution"
Requires-Dist: timm==0.9.10; extra == "super-resolution"
Requires-Dist: torchsr==1.0.4; extra == "super-resolution"
Requires-Dist: clearml==2.0.1; extra == "super-resolution"
Requires-Dist: pandas==2.1.3; extra == "super-resolution"
Requires-Dist: pytest==7.4.3; extra == "super-resolution"
Requires-Dist: natsort==8.4.0; extra == "super-resolution"
Requires-Dist: colorama==0.4.6; extra == "super-resolution"
Requires-Dist: python-box==7.1.1; extra == "super-resolution"
Requires-Dist: scikit-learn==1.3.2; extra == "super-resolution"
Requires-Dist: albumentations==1.3.1; extra == "super-resolution"
Requires-Dist: pytorch-lightning==2.5.2; extra == "super-resolution"
Requires-Dist: beautifulsoup4==4.12.2; extra == "super-resolution"
Requires-Dist: transformers==4.36.2; extra == "super-resolution"
Requires-Dist: lion-pytorch==0.1.2; extra == "super-resolution"
Requires-Dist: streamlit==1.30.0; extra == "super-resolution"
Requires-Dist: python-multipart==0.0.7; extra == "super-resolution"
Requires-Dist: empatches==0.2.3; extra == "super-resolution"
Requires-Dist: pillow==10.3.0; extra == "super-resolution"
Requires-Dist: imagecodecs==2024.6.1; extra == "super-resolution"
Requires-Dist: numpy==1.26.4; extra == "super-resolution"
Provides-Extra: full
Requires-Dist: dask<2025.4.1,>=2024.9.0; extra == "full"
Requires-Dist: geopandas<=1.0.1; extra == "full"
Requires-Dist: pillow<11.2.0,>=10.0.0; extra == "full"
Requires-Dist: planetary_computer<=1.0.0; extra == "full"
Requires-Dist: pystac<=1.12.2; extra == "full"
Requires-Dist: pystac_client<=0.8.6; extra == "full"
Requires-Dist: requests<=2.32.3; extra == "full"
Requires-Dist: rioxarray<=0.18.2; extra == "full"
Requires-Dist: stac_geoparquet<=0.6.0; extra == "full"
Requires-Dist: stackstac<=0.5.1; extra == "full"
Requires-Dist: shapely<=2.0.7; extra == "full"
Requires-Dist: numpy<=1.26.4; extra == "full"
Requires-Dist: tqdm<=4.67.1; extra == "full"
Requires-Dist: rasterio<=1.4.3; extra == "full"
Requires-Dist: torch>=2.6.0; extra == "full"
Requires-Dist: torchvision>=0.22.1; extra == "full"
Requires-Dist: torchaudio>=2.6.0; extra == "full"
Requires-Dist: opencv-python>=4.11.0.86; extra == "full"
Requires-Dist: scikit-image>=0.22.0; extra == "full"
Requires-Dist: tqdm>=4.66.1; extra == "full"
Requires-Dist: madgrad==1.3; extra == "full"
Requires-Dist: matplotlib==3.8.1; extra == "full"
Requires-Dist: timm==0.9.10; extra == "full"
Requires-Dist: torchsr==1.0.4; extra == "full"
Requires-Dist: clearml==2.0.1; extra == "full"
Requires-Dist: pandas==2.1.3; extra == "full"
Requires-Dist: pytest==7.4.3; extra == "full"
Requires-Dist: natsort==8.4.0; extra == "full"
Requires-Dist: colorama==0.4.6; extra == "full"
Requires-Dist: python-box==7.1.1; extra == "full"
Requires-Dist: scikit-learn==1.3.2; extra == "full"
Requires-Dist: albumentations==1.3.1; extra == "full"
Requires-Dist: pytorch-lightning==2.5.2; extra == "full"
Requires-Dist: beautifulsoup4==4.12.2; extra == "full"
Requires-Dist: transformers==4.36.2; extra == "full"
Requires-Dist: lion-pytorch==0.1.2; extra == "full"
Requires-Dist: streamlit==1.30.0; extra == "full"
Requires-Dist: python-multipart==0.0.7; extra == "full"
Requires-Dist: empatches==0.2.3; extra == "full"
Requires-Dist: pillow==10.3.0; extra == "full"
Requires-Dist: imagecodecs==2024.6.1; extra == "full"
Requires-Dist: numpy==1.26.4; extra == "full"
Dynamic: license-file
